twitter_utilities/__init__.py
twitter_utilities/utilities.py
aqad_utilities-0.1.4.dist-info/METADATA
aqad_utilities-0.1.4.dist-info/WHEEL
aqad_utilities-0.1.4.dist-info/top_level.txt
aqad_utilities-0.1.4.dist-info/RECORD
