Metadata-Version: 2.1
Name: aqad-utilities
Version: 0.1.4
Summary: Utility package for aqad
Home-page: https://github.com/mohit2152sharma/aqad-utilities/
Author: Mohit Sharma
Author-email: mohitsharma@alumni.iitm.ac.in
License: MIT
Platform: UNKNOWN
Classifier: License :: OSI Approved :: MIT License
Classifier: Programming Language :: Python
Classifier: Programming Language :: Python :: 3
Classifier: Programming Language :: Python :: 3.6
Requires-Python: >=3.6.0
